airflow/__init__.py
airflow/alembic.ini
airflow/configuration.py
airflow/default_login.py
airflow/exceptions.py
airflow/git_version
airflow/logging_config.py
airflow/plugins_manager.py
airflow/sentry.py
airflow/settings.py
airflow/typing_compat.py
airflow/version.py
airflow/api/__init__.py
airflow/api/auth/__init__.py
airflow/api/auth/backend/__init__.py
airflow/api/auth/backend/default.py
airflow/api/auth/backend/deny_all.py
airflow/api/auth/backend/kerberos_auth.py
airflow/api/client/__init__.py
airflow/api/client/api_client.py
airflow/api/client/json_client.py
airflow/api/client/local_client.py
airflow/api/common/__init__.py
airflow/api/common/experimental/__init__.py
airflow/api/common/experimental/delete_dag.py
airflow/api/common/experimental/get_code.py
airflow/api/common/experimental/get_dag_run_state.py
airflow/api/common/experimental/get_dag_runs.py
airflow/api/common/experimental/get_task.py
airflow/api/common/experimental/get_task_instance.py
airflow/api/common/experimental/mark_tasks.py
airflow/api/common/experimental/pool.py
airflow/api/common/experimental/trigger_dag.py
airflow/bin/__init__.py
airflow/bin/airflow
airflow/bin/cli.py
airflow/config_templates/__init__.py
airflow/config_templates/airflow_local_settings.py
airflow/config_templates/config.yml
airflow/config_templates/default_airflow.cfg
airflow/config_templates/default_celery.py
airflow/config_templates/default_test.cfg
airflow/config_templates/default_webserver_config.py
airflow/contrib/__init__.py
airflow/contrib/auth/__init__.py
airflow/contrib/auth/backends/__init__.py
airflow/contrib/auth/backends/github_enterprise_auth.py
airflow/contrib/auth/backends/google_auth.py
airflow/contrib/auth/backends/kerberos_auth.py
airflow/contrib/auth/backends/ldap_auth.py
airflow/contrib/auth/backends/password_auth.py
airflow/contrib/example_dags/__init__.py
airflow/contrib/example_dags/example_azure_container_instances_operator.py
airflow/contrib/example_dags/example_azure_cosmosdb_sensor.py
apache_airflow_zack-1.10.15.9.dist-info/LICENSE
apache_airflow_zack-1.10.15.9.dist-info/LICENSE-bootstrap-toggle.txt
apache_airflow_zack-1.10.15.9.dist-info/LICENSE-bootstrap.txt
apache_airflow_zack-1.10.15.9.dist-info/LICENSE-bootstrap3-typeahead.txt
apache_airflow_zack-1.10.15.9.dist-info/LICENSE-d3-tip.txt
apache_airflow_zack-1.10.15.9.dist-info/LICENSE-d3js.txt
apache_airflow_zack-1.10.15.9.dist-info/LICENSE-dagre-d3.txt
apache_airflow_zack-1.10.15.9.dist-info/LICENSE-datatables.txt
apache_airflow_zack-1.10.15.9.dist-info/LICENSE-elasticmock.txt
apache_airflow_zack-1.10.15.9.dist-info/LICENSE-eonasdan-bootstrap-datetimepicker.txt
apache_airflow_zack-1.10.15.9.dist-info/LICENSE-flask-kerberos.txt
apache_airflow_zack-1.10.15.9.dist-info/LICENSE-hue.txt
apache_airflow_zack-1.10.15.9.dist-info/LICENSE-jqclock.txt
apache_airflow_zack-1.10.15.9.dist-info/LICENSE-jquery.txt
apache_airflow_zack-1.10.15.9.dist-info/LICENSE-moment-strftime.txt
apache_airflow_zack-1.10.15.9.dist-info/LICENSE-moment.txt
apache_airflow_zack-1.10.15.9.dist-info/LICENSE-normalize.txt
apache_airflow_zack-1.10.15.9.dist-info/LICENSE-python-nvd3.txt
apache_airflow_zack-1.10.15.9.dist-info/LICENSE-python-slugify.txt
apache_airflow_zack-1.10.15.9.dist-info/METADATA
apache_airflow_zack-1.10.15.9.dist-info/NOTICE
apache_airflow_zack-1.10.15.9.dist-info/WHEEL
apache_airflow_zack-1.10.15.9.dist-info/top_level.txt
apache_airflow_zack-1.10.15.9.dist-info/RECORD
