Metadata-Version: 2.1
Name: apache-airflow-zack
Version: 1.10.15.9
Summary: Programmatically author, schedule and monitor data pipelines
Home-page: http://airflow.apache.org/
Author: Apache Software Foundation
Author-email: dev@airflow.apache.org
License: Apache License 2.0
Download-URL: https://archive.apache.org/dist/airflow/1.10.15
Project-URL: Documentation, https://airflow.apache.org/docs/
Project-URL: Bug Tracker, https://github.com/apache/airflow/issues
Project-URL: Source Code, https://github.com/apache/airflow
Platform: UNKNOWN
Classifier: Development Status :: 5 - Production/Stable
Classifier: Environment :: Console
Classifier: Environment :: Web Environment
Classifier: Intended Audience :: Developers
Classifier: Intended Audience :: System Administrators
Classifier: License :: OSI Approved :: Apache Software License
Classifier: Programming Language :: Python :: 2.7
Classifier: Programming Language :: Python :: 3.5
Classifier: Programming Language :: Python :: 3.6
Classifier: Programming Language :: Python :: 3.7
Classifier: Programming Language :: Python :: 3.8
Classifier: Topic :: System :: Monitoring
Requires-Python: >=2.7,!=3.0.*,!=3.1.*,!=3.2.*,!=3.3.*,!=3.4.*
License-File: LICENSE
License-File: NOTICE
License-File: licenses/LICENSE-bootstrap-toggle.txt
License-File: licenses/LICENSE-bootstrap.txt
License-File: licenses/LICENSE-bootstrap3-typeahead.txt
License-File: licenses/LICENSE-d3-tip.txt
License-File: licenses/LICENSE-d3js.txt
License-File: licenses/LICENSE-dagre-d3.txt
License-File: licenses/LICENSE-datatables.txt
License-File: licenses/LICENSE-elasticmock.txt
License-File: licenses/LICENSE-eonasdan-bootstrap-datetimepicker.txt
License-File: licenses/LICENSE-flask-kerberos.txt
License-File: licenses/LICENSE-hue.txt
License-File: licenses/LICENSE-jqclock.txt
License-File: licenses/LICENSE-jquery.txt
License-File: licenses/LICENSE-moment-strftime.txt
License-File: licenses/LICENSE-moment.txt
License-File: licenses/LICENSE-normalize.txt
License-File: licenses/LICENSE-python-nvd3.txt
License-File: licenses/LICENSE-python-slugify.txt
Requires-Dist: alembic (<2.0,>=1.0)
Requires-Dist: argcomplete (~=1.10)
Requires-Dist: attrs (<21.0,>=20.0)
Requires-Dist: cached-property (~=1.5)
Requires-Dist: colorlog (==4.0.2)
Requires-Dist: configparser (<3.6.0,>=3.5.0)
Requires-Dist: croniter (<0.4,>=0.3.17)
Requires-Dist: dill (<0.4,>=0.2.2)
Requires-Dist: email-validator
Requires-Dist: flask (<2.0,>=1.1.0)
Requires-Dist: flask-admin (==1.5.4)
Requires-Dist: flask-caching (==1.10.1)
Requires-Dist: flask-login (<0.5,>=0.3)
Requires-Dist: flask-swagger (<0.3,>=0.2.13)
Requires-Dist: flask-wtf (<0.15,>=0.14.2)
Requires-Dist: funcsigs (<2.0.0,>=1.0.0)
Requires-Dist: future (<0.19,>=0.16.0)
Requires-Dist: graphviz (>=0.12)
Requires-Dist: gunicorn (<21.0,>=19.5.0)
Requires-Dist: importlib-resources (~=1.4)
Requires-Dist: iso8601 (>=0.1.12)
Requires-Dist: jinja2 (<2.12.0,>=2.10.1)
Requires-Dist: json-merge-patch (==0.2)
Requires-Dist: jsonschema (~=3.0)
Requires-Dist: lazy-object-proxy (<1.5.0)
Requires-Dist: markdown (<3.0,>=2.5.2)
Requires-Dist: packaging
Requires-Dist: pandas (<2.0,>=0.17.1)
Requires-Dist: pendulum (==1.4.4)
Requires-Dist: psutil (<6.0.0,>=4.2.0)
Requires-Dist: pygments (<3.0,>=2.0.1)
Requires-Dist: python-daemon (>=2.1.1)
Requires-Dist: python-dateutil (<3,>=2.3)
Requires-Dist: python-nvd3 (~=0.15.0)
Requires-Dist: python-slugify (<5.0,>=3.0.0)
Requires-Dist: setproctitle (<2,>=1.1.8)
Requires-Dist: sqlalchemy (~=1.3)
Requires-Dist: tabulate (<0.9,>=0.7.5)
Requires-Dist: tenacity (==4.12.0)
Requires-Dist: thrift (>=0.11.0)
Requires-Dist: tzlocal (<2.0.0,>=1.4)
Requires-Dist: unicodecsv (>=0.14.1)
Requires-Dist: werkzeug (<1.0.0)
Requires-Dist: zope.deprecation (<5.0,>=4.0)
Requires-Dist: click (<8.0.0) ; python_version < "3.0"
Requires-Dist: cryptography (<3.0,>=0.9.3) ; python_version < "3.0"
Requires-Dist: requests (<2.23.0,>=2.20.0) ; python_version < "3.0"
Requires-Dist: enum34 (~=1.1.6) ; python_version < "3.4"
Requires-Dist: sqlalchemy-jsonfield (==0.8.0) ; python_version < "3.5"
Requires-Dist: typing ; python_version < "3.5"
Requires-Dist: flask-appbuilder (<2.0.0,>=1.12.2) ; python_version < "3.6"
Requires-Dist: marshmallow-sqlalchemy (<0.19.0,>=0.16.1) ; python_version < "3.6"
Requires-Dist: pep562 (~=1.0) ; python_version < "3.7"
Requires-Dist: typing-extensions (>=3.7.4) ; python_version < "3.8"
Requires-Dist: importlib-metadata (~=2.0) ; python_version < "3.9"
Requires-Dist: cattrs (<1.1.0,>=1.0) ; python_version <= "3.6"
Requires-Dist: cattrs (<2.0,>=1.0) ; python_version > "3.6"
Requires-Dist: cryptography (>=0.9.3) ; python_version >= "3.0"
Requires-Dist: requests (<2.24.0,>=2.20.0) ; python_version >= "3.0"
Requires-Dist: sqlalchemy-jsonfield (~=0.9) ; python_version >= "3.5"
Requires-Dist: flask-appbuilder (~=2.2) ; python_version >= "3.6"
Requires-Dist: marshmallow-sqlalchemy (<0.24.0,>=0.16.1) ; python_version >= "3.6"
Provides-Extra: all
Requires-Dist: cassandra-driver (<3.21.0,>=3.13.0) ; extra == 'all'
Requires-Dist: cloudant (<2.0,>=0.5.9) ; extra == 'all'
Requires-Dist: pydruid (<=0.5.8,>=0.4.1) ; extra == 'all'
Requires-Dist: hmsclient (>=0.1.0) ; extra == 'all'
Requires-Dist: pyhive[hive] (>=0.6.0) ; extra == 'all'
Requires-Dist: dnspython (<2.0.0,>=1.13.0) ; extra == 'all'
Requires-Dist: pymongo (<3.11.0,>=3.6.0) ; extra == 'all'
Requires-Dist: mysqlclient (<1.4,>=1.3.6) ; extra == 'all'
Requires-Dist: pinotdb (==0.1.1) ; extra == 'all'
Requires-Dist: psycopg2-binary (>=2.7.4) ; extra == 'all'
Requires-Dist: presto-python-client (<0.8,>=0.7.0) ; extra == 'all'
Requires-Dist: vertica-python (>=0.5.1) ; extra == 'all'
Requires-Dist: atlasclient (>=0.1.2) ; extra == 'all'
Requires-Dist: boto3 (~=1.10) ; extra == 'all'
Requires-Dist: azure-storage (<0.37.0,>=0.34.0) ; extra == 'all'
Requires-Dist: azure-storage-common ; extra == 'all'
Requires-Dist: azure-mgmt-containerinstance (<2,>=1.5.0) ; extra == 'all'
Requires-Dist: azure-cosmos (<4,>=3.0.1) ; extra == 'all'
Requires-Dist: azure-datalake-store (>=0.0.45) ; extra == 'all'
Requires-Dist: azure-mgmt-datalake-store (>=0.5.0) ; extra == 'all'
Requires-Dist: azure-mgmt-resource (>=2.2.0) ; extra == 'all'
Requires-Dist: azure-identity (>=1.3.1) ; extra == 'all'
Requires-Dist: azure-keyvault (>=4.1.0) ; extra == 'all'
Requires-Dist: cgroupspy (>=0.1.4) ; extra == 'all'
Requires-Dist: beautifulsoup4 (~=4.7.1) ; extra == 'all'
Requires-Dist: click (==6.7) ; extra == 'all'
Requires-Dist: coverage ; extra == 'all'
Requires-Dist: docutils (<0.16,>=0.14) ; extra == 'all'
Requires-Dist: ecdsa (<0.15) ; extra == 'all'
Requires-Dist: flake8 (>=3.6.0) ; extra == 'all'
Requires-Dist: flake8-colors ; extra == 'all'
Requires-Dist: flaky ; extra == 'all'
Requires-Dist: freezegun ; extra == 'all'
Requires-Dist: gitpython ; extra == 'all'
Requires-Dist: idna (<2.9) ; extra == 'all'
Requires-Dist: ipdb ; extra == 'all'
Requires-Dist: jira ; extra == 'all'
Requires-Dist: mongomock ; extra == 'all'
Requires-Dist: moto (==1.3.14) ; extra == 'all'
Requires-Dist: packaging ; extra == 'all'
Requires-Dist: parameterized ; extra == 'all'
Requires-Dist: paramiko ; extra == 'all'
Requires-Dist: pipdeptree ; extra == 'all'
Requires-Dist: pre-commit ; extra == 'all'
Requires-Dist: pysftp ; extra == 'all'
Requires-Dist: pytest (<6.0.0) ; extra == 'all'
Requires-Dist: pytest-cov ; extra == 'all'
Requires-Dist: pytest-instafail ; extra == 'all'
Requires-Dist: pytest-timeouts ; extra == 'all'
Requires-Dist: pywinrm ; extra == 'all'
Requires-Dist: qds-sdk (>=1.9.6) ; extra == 'all'
Requires-Dist: requests-mock ; extra == 'all'
Requires-Dist: yamllint ; extra == 'all'
Requires-Dist: mypy (==0.720) ; extra == 'all'
Requires-Dist: sphinx-argparse (>=0.1.13) ; extra == 'all'
Requires-Dist: sphinx-autoapi (==1.0.0) ; extra == 'all'
Requires-Dist: sphinx-jinja (~=1.1) ; extra == 'all'
Requires-Dist: sphinx-rtd-theme (>=0.1.6) ; extra == 'all'
Requires-Dist: sphinxcontrib-httpdomain (>=1.7.0) ; extra == 'all'
Requires-Dist: cryptography (>=2.0.0) ; extra == 'all'
Requires-Dist: kubernetes (<12.0.0,>=3.0.0) ; extra == 'all'
Requires-Dist: bcrypt (>=2.0.0) ; extra == 'all'
Requires-Dist: flask-bcrypt (>=0.7.1) ; extra == 'all'
Requires-Dist: flower (<1.0,>=0.7.3) ; extra == 'all'
Requires-Dist: tornado (<6.0,>=4.2.0) ; extra == 'all'
Requires-Dist: vine (~=1.3) ; extra == 'all'
Requires-Dist: datadog (>=0.14.0) ; extra == 'all'
Requires-Dist: docker (~=3.0) ; extra == 'all'
Requires-Dist: elasticsearch (<6.0.0,>=5.0.0) ; extra == 'all'
Requires-Dist: elasticsearch-dsl (<6.0.0,>=5.0.0) ; extra == 'all'
Requires-Dist: google-api-python-client (<2.0.0,>=1.6.0) ; extra == 'all'
Requires-Dist: google-auth (<2.0.0,>=1.0.0) ; extra == 'all'
Requires-Dist: google-auth-httplib2 (>=0.0.1) ; extra == 'all'
Requires-Dist: google-cloud-bigtable (<2.0.0,>=1.0.0) ; extra == 'all'
Requires-Dist: google-cloud-container (<2.0.0,>=0.1.1) ; extra == 'all'
Requires-Dist: google-cloud-dlp (<2.0.0,>=0.11.0) ; extra == 'all'
Requires-Dist: google-cloud-language (<2.0.0,>=1.1.1) ; extra == 'all'
Requires-Dist: google-cloud-secret-manager (<2.0.0,>=0.2.0) ; extra == 'all'
Requires-Dist: google-cloud-spanner (<2.0.0,>=1.10.0) ; extra == 'all'
Requires-Dist: google-cloud-speech (<2.0.0,>=0.36.3) ; extra == 'all'
Requires-Dist: google-cloud-storage (<2.0.0,>=1.16) ; extra == 'all'
Requires-Dist: google-cloud-texttospeech (<2,>=0.4.0) ; extra == 'all'
Requires-Dist: google-cloud-translate (<2.0.0,>=1.3.3) ; extra == 'all'
Requires-Dist: google-cloud-videointelligence (<2.0.0,>=1.7.0) ; extra == 'all'
Requires-Dist: google-cloud-vision (<2.0.0,>=0.35.2) ; extra == 'all'
Requires-Dist: grpcio-gcp (>=0.2.2) ; extra == 'all'
Requires-Dist: pandas-gbq ; extra == 'all'
Requires-Dist: grpcio (>=1.15.0) ; extra == 'all'
Requires-Dist: hvac (~=0.10) ; extra == 'all'
Requires-Dist: JPype1 (==0.7.1) ; extra == 'all'
Requires-Dist: jaydebeapi (>=1.1.1) ; extra == 'all'
Requires-Dist: python-jenkins (>=1.0.0) ; extra == 'all'
Requires-Dist: pykerberos (>=1.1.13) ; extra == 'all'
Requires-Dist: requests-kerberos (>=0.10.0) ; extra == 'all'
Requires-Dist: ldap3 (>=2.5.1) ; extra == 'all'
Requires-Dist: papermill[all] (>=1.0.0) ; extra == 'all'
Requires-Dist: nteract-scrapbook[all] (>=0.2.1) ; extra == 'all'
Requires-Dist: pyarrow (<1.0.0) ; extra == 'all'
Requires-Dist: amqp (<5.0.0) ; extra == 'all'
Requires-Dist: redis (~=3.2) ; extra == 'all'
Requires-Dist: pysmbclient (>=0.1.3) ; extra == 'all'
Requires-Dist: analytics-python (>=1.2.9) ; extra == 'all'
Requires-Dist: sendgrid (<6,>=5.2.0) ; extra == 'all'
Requires-Dist: blinker (>=1.1) ; extra == 'all'
Requires-Dist: sentry-sdk (>=0.8.0) ; extra == 'all'
Requires-Dist: slackclient (<2.0.0,>=1.0.0) ; extra == 'all'
Requires-Dist: websocket-client (<0.55.0) ; extra == 'all'
Requires-Dist: boto3 (<1.11) ; extra == 'all'
Requires-Dist: snowflake-connector-python (>=1.5.2) ; extra == 'all'
Requires-Dist: snowflake-sqlalchemy (>=1.1.0) ; extra == 'all'
Requires-Dist: paramiko (>=2.1.1) ; extra == 'all'
Requires-Dist: pysftp (>=0.2.9) ; extra == 'all'
Requires-Dist: sshtunnel (<0.2,>=0.1.4) ; extra == 'all'
Requires-Dist: virtualenv ; extra == 'all'
Requires-Dist: hdfs[avro,dataframe,kerberos] (>=2.0.4) ; extra == 'all'
Requires-Dist: zdesk ; extra == 'all'
Requires-Dist: snakebite (>=2.7.8) ; (python_version < "3.0") and extra == 'all'
Requires-Dist: cffi (<1.14.0) ; (python_version < "3.0") and extra == 'all'
Requires-Dist: pyrsistent (<=0.16.0) ; (python_version < "3.0") and extra == 'all'
Requires-Dist: sphinx (==1.8.5) ; (python_version < "3.0") and extra == 'all'
Requires-Dist: celery (==4.3.1) ; (python_version < "3.0") and extra == 'all'
Requires-Dist: kombu (==4.6.3) ; (python_version < "3.0") and extra == 'all'
Requires-Dist: cryptography (<3.0,>=0.9.3) ; (python_version < "3.0") and extra == 'all'
Requires-Dist: PyOpenSSL (<20.0.0) ; (python_version < "3.0") and extra == 'all'
Requires-Dist: thrift-sasl (<0.4.1,>=0.2.0) ; (python_version < "3.0") and extra == 'all'
Requires-Dist: cx-Oracle (<8.0,>=5.1.2) ; (python_version < "3.0") and extra == 'all'
Requires-Dist: mock ; (python_version < "3.3") and extra == 'all'
Requires-Dist: contextdecorator ; (python_version < "3.4") and extra == 'all'
Requires-Dist: azure-storage-blob (<12.0.0) ; (python_version < "3.6") and extra == 'all'
Requires-Dist: importlib-metadata (~=2.0) ; (python_version < "3.9") and extra == 'all'
Requires-Dist: fsspec (<0.8.0) ; (python_version == "3.5") and extra == 'all'
Requires-Dist: snakebite-py3 ; (python_version >= "3.0") and extra == 'all'
Requires-Dist: pyrsistent ; (python_version >= "3.0") and extra == 'all'
Requires-Dist: sphinx (>=2.1.2) ; (python_version >= "3.0") and extra == 'all'
Requires-Dist: celery (~=4.3) ; (python_version >= "3.0") and extra == 'all'
Requires-Dist: cryptography (>=0.9.3) ; (python_version >= "3.0") and extra == 'all'
Requires-Dist: PyOpenSSL ; (python_version >= "3.0") and extra == 'all'
Requires-Dist: thrift-sasl (>=0.2.0) ; (python_version >= "3.0") and extra == 'all'
Requires-Dist: cx-Oracle (>=5.1.2) ; (python_version >= "3.0") and extra == 'all'
Requires-Dist: azure-storage-blob ; (python_version >= "3.6") and extra == 'all'
Requires-Dist: sphinx-copybutton ; (python_version >= "3.6") and extra == 'all'
Requires-Dist: black (==20.8b0) ; (python_version >= "3.6") and extra == 'all'
Provides-Extra: all_dbs
Requires-Dist: cassandra-driver (<3.21.0,>=3.13.0) ; extra == 'all_dbs'
Requires-Dist: cloudant (<2.0,>=0.5.9) ; extra == 'all_dbs'
Requires-Dist: pydruid (<=0.5.8,>=0.4.1) ; extra == 'all_dbs'
Requires-Dist: hmsclient (>=0.1.0) ; extra == 'all_dbs'
Requires-Dist: pyhive[hive] (>=0.6.0) ; extra == 'all_dbs'
Requires-Dist: dnspython (<2.0.0,>=1.13.0) ; extra == 'all_dbs'
Requires-Dist: pymongo (<3.11.0,>=3.6.0) ; extra == 'all_dbs'
Requires-Dist: pymssql (~=2.1.1) ; extra == 'all_dbs'
Requires-Dist: mysqlclient (<1.4,>=1.3.6) ; extra == 'all_dbs'
Requires-Dist: pinotdb (==0.1.1) ; extra == 'all_dbs'
Requires-Dist: psycopg2-binary (>=2.7.4) ; extra == 'all_dbs'
Requires-Dist: presto-python-client (<0.8,>=0.7.0) ; extra == 'all_dbs'
Requires-Dist: vertica-python (>=0.5.1) ; extra == 'all_dbs'
Requires-Dist: snakebite (>=2.7.8) ; (python_version < "3.0") and extra == 'all_dbs'
Requires-Dist: snakebite-py3 ; (python_version >= "3.0") and extra == 'all_dbs'
Provides-Extra: amazon
Requires-Dist: boto3 (~=1.10) ; extra == 'amazon'
Provides-Extra: apache.atlas
Requires-Dist: atlasclient (>=0.1.2) ; extra == 'apache.atlas'
Provides-Extra: apache.cassandra
Requires-Dist: cassandra-driver (<3.21.0,>=3.13.0) ; extra == 'apache.cassandra'
Provides-Extra: apache.druid
Requires-Dist: pydruid (<=0.5.8,>=0.4.1) ; extra == 'apache.druid'
Provides-Extra: apache.hdfs
Requires-Dist: snakebite (>=2.7.8) ; (python_version < "3.0") and extra == 'apache.hdfs'
Requires-Dist: snakebite-py3 ; (python_version >= "3.0") and extra == 'apache.hdfs'
Provides-Extra: apache.hive
Requires-Dist: hmsclient (>=0.1.0) ; extra == 'apache.hive'
Requires-Dist: pyhive[hive] (>=0.6.0) ; extra == 'apache.hive'
Provides-Extra: apache.pinot
Requires-Dist: pinotdb (==0.1.1) ; extra == 'apache.pinot'
Provides-Extra: apache.presto
Requires-Dist: presto-python-client (<0.8,>=0.7.0) ; extra == 'apache.presto'
Provides-Extra: apache.webhdfs
Requires-Dist: hdfs[avro,dataframe,kerberos] (>=2.0.4) ; extra == 'apache.webhdfs'
Provides-Extra: async
Requires-Dist: eventlet (>=0.9.7) ; extra == 'async'
Requires-Dist: gevent (>=0.13) ; extra == 'async'
Requires-Dist: greenlet (>=0.4.9) ; extra == 'async'
Provides-Extra: atlas
Requires-Dist: atlasclient (>=0.1.2) ; extra == 'atlas'
Provides-Extra: aws
Requires-Dist: boto3 (~=1.10) ; extra == 'aws'
Provides-Extra: azure
Requires-Dist: azure-storage (<0.37.0,>=0.34.0) ; extra == 'azure'
Requires-Dist: azure-storage-common ; extra == 'azure'
Requires-Dist: azure-mgmt-containerinstance (<2,>=1.5.0) ; extra == 'azure'
Requires-Dist: azure-cosmos (<4,>=3.0.1) ; extra == 'azure'
Requires-Dist: azure-datalake-store (>=0.0.45) ; extra == 'azure'
Requires-Dist: azure-mgmt-datalake-store (>=0.5.0) ; extra == 'azure'
Requires-Dist: azure-mgmt-resource (>=2.2.0) ; extra == 'azure'
Requires-Dist: azure-identity (>=1.3.1) ; extra == 'azure'
Requires-Dist: azure-keyvault (>=4.1.0) ; extra == 'azure'
Requires-Dist: cffi (<1.14.0) ; (python_version < "3.0") and extra == 'azure'
Requires-Dist: azure-storage-blob (<12.0.0) ; (python_version < "3.6") and extra == 'azure'
Requires-Dist: azure-storage-blob ; (python_version >= "3.6") and extra == 'azure'
Provides-Extra: azure_blob_storage
Requires-Dist: azure-storage (<0.37.0,>=0.34.0) ; extra == 'azure_blob_storage'
Requires-Dist: azure-storage-common ; extra == 'azure_blob_storage'
Requires-Dist: azure-storage-blob (<12.0.0) ; (python_version < "3.6") and extra == 'azure_blob_storage'
Requires-Dist: azure-storage-blob ; (python_version >= "3.6") and extra == 'azure_blob_storage'
Provides-Extra: azure_container_instances
Requires-Dist: azure-mgmt-containerinstance (<2,>=1.5.0) ; extra == 'azure_container_instances'
Provides-Extra: azure_cosmos
Requires-Dist: azure-cosmos (<4,>=3.0.1) ; extra == 'azure_cosmos'
Provides-Extra: azure_data_lake
Requires-Dist: azure-datalake-store (>=0.0.45) ; extra == 'azure_data_lake'
Requires-Dist: azure-mgmt-datalake-store (>=0.5.0) ; extra == 'azure_data_lake'
Requires-Dist: azure-mgmt-resource (>=2.2.0) ; extra == 'azure_data_lake'
Requires-Dist: cffi (<1.14.0) ; (python_version < "3.0") and extra == 'azure_data_lake'
Provides-Extra: azure_secrets
Requires-Dist: azure-identity (>=1.3.1) ; extra == 'azure_secrets'
Requires-Dist: azure-keyvault (>=4.1.0) ; extra == 'azure_secrets'
Provides-Extra: cassandra
Requires-Dist: cassandra-driver (<3.21.0,>=3.13.0) ; extra == 'cassandra'
Provides-Extra: celery
Requires-Dist: flower (<1.0,>=0.7.3) ; extra == 'celery'
Requires-Dist: tornado (<6.0,>=4.2.0) ; extra == 'celery'
Requires-Dist: vine (~=1.3) ; extra == 'celery'
Requires-Dist: celery (==4.3.1) ; (python_version < "3.0") and extra == 'celery'
Requires-Dist: kombu (==4.6.3) ; (python_version < "3.0") and extra == 'celery'
Requires-Dist: celery (~=4.3) ; (python_version >= "3.0") and extra == 'celery'
Provides-Extra: cgroups
Requires-Dist: cgroupspy (>=0.1.4) ; extra == 'cgroups'
Provides-Extra: cloudant
Requires-Dist: cloudant (<2.0,>=0.5.9) ; extra == 'cloudant'
Provides-Extra: cncf.kubernetes
Requires-Dist: cryptography (>=2.0.0) ; extra == 'cncf.kubernetes'
Requires-Dist: kubernetes (<12.0.0,>=3.0.0) ; extra == 'cncf.kubernetes'
Provides-Extra: crypto
Requires-Dist: cryptography (<3.0,>=0.9.3) ; (python_version < "3.0") and extra == 'crypto'
Requires-Dist: cryptography (>=0.9.3) ; (python_version >= "3.0") and extra == 'crypto'
Provides-Extra: dask
Requires-Dist: distributed (<2,>=1.17.1) ; extra == 'dask'
Provides-Extra: databricks
Requires-Dist: requests (<3,>=2.20.0) ; extra == 'databricks'
Provides-Extra: datadog
Requires-Dist: datadog (>=0.14.0) ; extra == 'datadog'
Provides-Extra: devel
Requires-Dist: boto3 (~=1.10) ; extra == 'devel'
Requires-Dist: cgroupspy (>=0.1.4) ; extra == 'devel'
Requires-Dist: beautifulsoup4 (~=4.7.1) ; extra == 'devel'
Requires-Dist: click (==6.7) ; extra == 'devel'
Requires-Dist: coverage ; extra == 'devel'
Requires-Dist: docutils (<0.16,>=0.14) ; extra == 'devel'
Requires-Dist: ecdsa (<0.15) ; extra == 'devel'
Requires-Dist: flake8 (>=3.6.0) ; extra == 'devel'
Requires-Dist: flake8-colors ; extra == 'devel'
Requires-Dist: flaky ; extra == 'devel'
Requires-Dist: freezegun ; extra == 'devel'
Requires-Dist: gitpython ; extra == 'devel'
Requires-Dist: idna (<2.9) ; extra == 'devel'
Requires-Dist: ipdb ; extra == 'devel'
Requires-Dist: jira ; extra == 'devel'
Requires-Dist: mongomock ; extra == 'devel'
Requires-Dist: moto (==1.3.14) ; extra == 'devel'
Requires-Dist: packaging ; extra == 'devel'
Requires-Dist: parameterized ; extra == 'devel'
Requires-Dist: paramiko ; extra == 'devel'
Requires-Dist: pipdeptree ; extra == 'devel'
Requires-Dist: pre-commit ; extra == 'devel'
Requires-Dist: pysftp ; extra == 'devel'
Requires-Dist: pytest (<6.0.0) ; extra == 'devel'
Requires-Dist: pytest-cov ; extra == 'devel'
Requires-Dist: pytest-instafail ; extra == 'devel'
Requires-Dist: pytest-timeouts ; extra == 'devel'
Requires-Dist: pywinrm ; extra == 'devel'
Requires-Dist: qds-sdk (>=1.9.6) ; extra == 'devel'
Requires-Dist: requests-mock ; extra == 'devel'
Requires-Dist: yamllint ; extra == 'devel'
Requires-Dist: mypy (==0.720) ; extra == 'devel'
Requires-Dist: sphinx-argparse (>=0.1.13) ; extra == 'devel'
Requires-Dist: sphinx-autoapi (==1.0.0) ; extra == 'devel'
Requires-Dist: sphinx-jinja (~=1.1) ; extra == 'devel'
Requires-Dist: sphinx-rtd-theme (>=0.1.6) ; extra == 'devel'
Requires-Dist: sphinxcontrib-httpdomain (>=1.7.0) ; extra == 'devel'
Requires-Dist: cryptography (>=2.0.0) ; extra == 'devel'
Requires-Dist: kubernetes (<12.0.0,>=3.0.0) ; extra == 'devel'
Requires-Dist: mysqlclient (<1.4,>=1.3.6) ; extra == 'devel'
Requires-Dist: bcrypt (>=2.0.0) ; extra == 'devel'
Requires-Dist: flask-bcrypt (>=0.7.1) ; extra == 'devel'
Requires-Dist: pyrsistent (<=0.16.0) ; (python_version < "3.0") and extra == 'devel'
Requires-Dist: sphinx (==1.8.5) ; (python_version < "3.0") and extra == 'devel'
Requires-Dist: mock ; (python_version < "3.3") and extra == 'devel'
Requires-Dist: contextdecorator ; (python_version < "3.4") and extra == 'devel'
Requires-Dist: importlib-metadata (~=2.0) ; (python_version < "3.9") and extra == 'devel'
Requires-Dist: pyrsistent ; (python_version >= "3.0") and extra == 'devel'
Requires-Dist: sphinx (>=2.1.2) ; (python_version >= "3.0") and extra == 'devel'
Requires-Dist: sphinx-copybutton ; (python_version >= "3.6") and extra == 'devel'
Provides-Extra: devel_all
Requires-Dist: cassandra-driver (<3.21.0,>=3.13.0) ; extra == 'devel_all'
Requires-Dist: cloudant (<2.0,>=0.5.9) ; extra == 'devel_all'
Requires-Dist: pydruid (<=0.5.8,>=0.4.1) ; extra == 'devel_all'
Requires-Dist: hmsclient (>=0.1.0) ; extra == 'devel_all'
Requires-Dist: pyhive[hive] (>=0.6.0) ; extra == 'devel_all'
Requires-Dist: dnspython (<2.0.0,>=1.13.0) ; extra == 'devel_all'
Requires-Dist: pymongo (<3.11.0,>=3.6.0) ; extra == 'devel_all'
Requires-Dist: mysqlclient (<1.4,>=1.3.6) ; extra == 'devel_all'
Requires-Dist: pinotdb (==0.1.1) ; extra == 'devel_all'
Requires-Dist: psycopg2-binary (>=2.7.4) ; extra == 'devel_all'
Requires-Dist: presto-python-client (<0.8,>=0.7.0) ; extra == 'devel_all'
Requires-Dist: vertica-python (>=0.5.1) ; extra == 'devel_all'
Requires-Dist: atlasclient (>=0.1.2) ; extra == 'devel_all'
Requires-Dist: boto3 (~=1.10) ; extra == 'devel_all'
Requires-Dist: azure-storage (<0.37.0,>=0.34.0) ; extra == 'devel_all'
Requires-Dist: azure-storage-common ; extra == 'devel_all'
Requires-Dist: azure-mgmt-containerinstance (<2,>=1.5.0) ; extra == 'devel_all'
Requires-Dist: azure-cosmos (<4,>=3.0.1) ; extra == 'devel_all'
Requires-Dist: azure-datalake-store (>=0.0.45) ; extra == 'devel_all'
Requires-Dist: azure-mgmt-datalake-store (>=0.5.0) ; extra == 'devel_all'
Requires-Dist: azure-mgmt-resource (>=2.2.0) ; extra == 'devel_all'
Requires-Dist: azure-identity (>=1.3.1) ; extra == 'devel_all'
Requires-Dist: azure-keyvault (>=4.1.0) ; extra == 'devel_all'
Requires-Dist: cgroupspy (>=0.1.4) ; extra == 'devel_all'
Requires-Dist: beautifulsoup4 (~=4.7.1) ; extra == 'devel_all'
Requires-Dist: click (==6.7) ; extra == 'devel_all'
Requires-Dist: coverage ; extra == 'devel_all'
Requires-Dist: docutils (<0.16,>=0.14) ; extra == 'devel_all'
Requires-Dist: ecdsa (<0.15) ; extra == 'devel_all'
Requires-Dist: flake8 (>=3.6.0) ; extra == 'devel_all'
Requires-Dist: flake8-colors ; extra == 'devel_all'
Requires-Dist: flaky ; extra == 'devel_all'
Requires-Dist: freezegun ; extra == 'devel_all'
Requires-Dist: gitpython ; extra == 'devel_all'
Requires-Dist: idna (<2.9) ; extra == 'devel_all'
Requires-Dist: ipdb ; extra == 'devel_all'
Requires-Dist: jira ; extra == 'devel_all'
Requires-Dist: mongomock ; extra == 'devel_all'
Requires-Dist: moto (==1.3.14) ; extra == 'devel_all'
Requires-Dist: packaging ; extra == 'devel_all'
Requires-Dist: parameterized ; extra == 'devel_all'
Requires-Dist: paramiko ; extra == 'devel_all'
Requires-Dist: pipdeptree ; extra == 'devel_all'
Requires-Dist: pre-commit ; extra == 'devel_all'
Requires-Dist: pysftp ; extra == 'devel_all'
Requires-Dist: pytest (<6.0.0) ; extra == 'devel_all'
Requires-Dist: pytest-cov ; extra == 'devel_all'
Requires-Dist: pytest-instafail ; extra == 'devel_all'
Requires-Dist: pytest-timeouts ; extra == 'devel_all'
Requires-Dist: pywinrm ; extra == 'devel_all'
Requires-Dist: qds-sdk (>=1.9.6) ; extra == 'devel_all'
Requires-Dist: requests-mock ; extra == 'devel_all'
Requires-Dist: yamllint ; extra == 'devel_all'
Requires-Dist: mypy (==0.720) ; extra == 'devel_all'
Requires-Dist: sphinx-argparse (>=0.1.13) ; extra == 'devel_all'
Requires-Dist: sphinx-autoapi (==1.0.0) ; extra == 'devel_all'
Requires-Dist: sphinx-jinja (~=1.1) ; extra == 'devel_all'
Requires-Dist: sphinx-rtd-theme (>=0.1.6) ; extra == 'devel_all'
Requires-Dist: sphinxcontrib-httpdomain (>=1.7.0) ; extra == 'devel_all'
Requires-Dist: cryptography (>=2.0.0) ; extra == 'devel_all'
Requires-Dist: kubernetes (<12.0.0,>=3.0.0) ; extra == 'devel_all'
Requires-Dist: bcrypt (>=2.0.0) ; extra == 'devel_all'
Requires-Dist: flask-bcrypt (>=0.7.1) ; extra == 'devel_all'
Requires-Dist: flower (<1.0,>=0.7.3) ; extra == 'devel_all'
Requires-Dist: tornado (<6.0,>=4.2.0) ; extra == 'devel_all'
Requires-Dist: vine (~=1.3) ; extra == 'devel_all'
Requires-Dist: datadog (>=0.14.0) ; extra == 'devel_all'
Requires-Dist: docker (~=3.0) ; extra == 'devel_all'
Requires-Dist: elasticsearch (<6.0.0,>=5.0.0) ; extra == 'devel_all'
Requires-Dist: elasticsearch-dsl (<6.0.0,>=5.0.0) ; extra == 'devel_all'
Requires-Dist: google-api-python-client (<2.0.0,>=1.6.0) ; extra == 'devel_all'
Requires-Dist: google-auth (<2.0.0,>=1.0.0) ; extra == 'devel_all'
Requires-Dist: google-auth-httplib2 (>=0.0.1) ; extra == 'devel_all'
Requires-Dist: google-cloud-bigtable (<2.0.0,>=1.0.0) ; extra == 'devel_all'
Requires-Dist: google-cloud-container (<2.0.0,>=0.1.1) ; extra == 'devel_all'
Requires-Dist: google-cloud-dlp (<2.0.0,>=0.11.0) ; extra == 'devel_all'
Requires-Dist: google-cloud-language (<2.0.0,>=1.1.1) ; extra == 'devel_all'
Requires-Dist: google-cloud-secret-manager (<2.0.0,>=0.2.0) ; extra == 'devel_all'
Requires-Dist: google-cloud-spanner (<2.0.0,>=1.10.0) ; extra == 'devel_all'
Requires-Dist: google-cloud-speech (<2.0.0,>=0.36.3) ; extra == 'devel_all'
Requires-Dist: google-cloud-storage (<2.0.0,>=1.16) ; extra == 'devel_all'
Requires-Dist: google-cloud-texttospeech (<2,>=0.4.0) ; extra == 'devel_all'
Requires-Dist: google-cloud-translate (<2.0.0,>=1.3.3) ; extra == 'devel_all'
Requires-Dist: google-cloud-videointelligence (<2.0.0,>=1.7.0) ; extra == 'devel_all'
Requires-Dist: google-cloud-vision (<2.0.0,>=0.35.2) ; extra == 'devel_all'
Requires-Dist: grpcio-gcp (>=0.2.2) ; extra == 'devel_all'
Requires-Dist: pandas-gbq ; extra == 'devel_all'
Requires-Dist: grpcio (>=1.15.0) ; extra == 'devel_all'
Requires-Dist: hvac (~=0.10) ; extra == 'devel_all'
Requires-Dist: JPype1 (==0.7.1) ; extra == 'devel_all'
Requires-Dist: jaydebeapi (>=1.1.1) ; extra == 'devel_all'
Requires-Dist: python-jenkins (>=1.0.0) ; extra == 'devel_all'
Requires-Dist: pykerberos (>=1.1.13) ; extra == 'devel_all'
Requires-Dist: requests-kerberos (>=0.10.0) ; extra == 'devel_all'
Requires-Dist: ldap3 (>=2.5.1) ; extra == 'devel_all'
Requires-Dist: papermill[all] (>=1.0.0) ; extra == 'devel_all'
Requires-Dist: nteract-scrapbook[all] (>=0.2.1) ; extra == 'devel_all'
Requires-Dist: pyarrow (<1.0.0) ; extra == 'devel_all'
Requires-Dist: amqp (<5.0.0) ; extra == 'devel_all'
Requires-Dist: redis (~=3.2) ; extra == 'devel_all'
Requires-Dist: pysmbclient (>=0.1.3) ; extra == 'devel_all'
Requires-Dist: analytics-python (>=1.2.9) ; extra == 'devel_all'
Requires-Dist: sendgrid (<6,>=5.2.0) ; extra == 'devel_all'
Requires-Dist: blinker (>=1.1) ; extra == 'devel_all'
Requires-Dist: sentry-sdk (>=0.8.0) ; extra == 'devel_all'
Requires-Dist: slackclient (<2.0.0,>=1.0.0) ; extra == 'devel_all'
Requires-Dist: websocket-client (<0.55.0) ; extra == 'devel_all'
Requires-Dist: boto3 (<1.11) ; extra == 'devel_all'
Requires-Dist: snowflake-connector-python (>=1.5.2) ; extra == 'devel_all'
Requires-Dist: snowflake-sqlalchemy (>=1.1.0) ; extra == 'devel_all'
Requires-Dist: paramiko (>=2.1.1) ; extra == 'devel_all'
Requires-Dist: pysftp (>=0.2.9) ; extra == 'devel_all'
Requires-Dist: sshtunnel (<0.2,>=0.1.4) ; extra == 'devel_all'
Requires-Dist: virtualenv ; extra == 'devel_all'
Requires-Dist: hdfs[avro,dataframe,kerberos] (>=2.0.4) ; extra == 'devel_all'
Requires-Dist: zdesk ; extra == 'devel_all'
Requires-Dist: snakebite (>=2.7.8) ; (python_version < "3.0") and extra == 'devel_all'
Requires-Dist: cffi (<1.14.0) ; (python_version < "3.0") and extra == 'devel_all'
Requires-Dist: pyrsistent (<=0.16.0) ; (python_version < "3.0") and extra == 'devel_all'
Requires-Dist: sphinx (==1.8.5) ; (python_version < "3.0") and extra == 'devel_all'
Requires-Dist: celery (==4.3.1) ; (python_version < "3.0") and extra == 'devel_all'
Requires-Dist: kombu (==4.6.3) ; (python_version < "3.0") and extra == 'devel_all'
Requires-Dist: cryptography (<3.0,>=0.9.3) ; (python_version < "3.0") and extra == 'devel_all'
Requires-Dist: PyOpenSSL (<20.0.0) ; (python_version < "3.0") and extra == 'devel_all'
Requires-Dist: thrift-sasl (<0.4.1,>=0.2.0) ; (python_version < "3.0") and extra == 'devel_all'
Requires-Dist: cx-Oracle (<8.0,>=5.1.2) ; (python_version < "3.0") and extra == 'devel_all'
Requires-Dist: mock ; (python_version < "3.3") and extra == 'devel_all'
Requires-Dist: contextdecorator ; (python_version < "3.4") and extra == 'devel_all'
Requires-Dist: azure-storage-blob (<12.0.0) ; (python_version < "3.6") and extra == 'devel_all'
Requires-Dist: importlib-metadata (~=2.0) ; (python_version < "3.9") and extra == 'devel_all'
Requires-Dist: fsspec (<0.8.0) ; (python_version == "3.5") and extra == 'devel_all'
Requires-Dist: snakebite-py3 ; (python_version >= "3.0") and extra == 'devel_all'
Requires-Dist: pyrsistent ; (python_version >= "3.0") and extra == 'devel_all'
Requires-Dist: sphinx (>=2.1.2) ; (python_version >= "3.0") and extra == 'devel_all'
Requires-Dist: celery (~=4.3) ; (python_version >= "3.0") and extra == 'devel_all'
Requires-Dist: cryptography (>=0.9.3) ; (python_version >= "3.0") and extra == 'devel_all'
Requires-Dist: PyOpenSSL ; (python_version >= "3.0") and extra == 'devel_all'
Requires-Dist: thrift-sasl (>=0.2.0) ; (python_version >= "3.0") and extra == 'devel_all'
Requires-Dist: cx-Oracle (>=5.1.2) ; (python_version >= "3.0") and extra == 'devel_all'
Requires-Dist: azure-storage-blob ; (python_version >= "3.6") and extra == 'devel_all'
Requires-Dist: sphinx-copybutton ; (python_version >= "3.6") and extra == 'devel_all'
Requires-Dist: black (==20.8b0) ; (python_version >= "3.6") and extra == 'devel_all'
Provides-Extra: devel_azure
Requires-Dist: azure-storage (<0.37.0,>=0.34.0) ; extra == 'devel_azure'
Requires-Dist: azure-storage-common ; extra == 'devel_azure'
Requires-Dist: azure-mgmt-containerinstance (<2,>=1.5.0) ; extra == 'devel_azure'
Requires-Dist: azure-cosmos (<4,>=3.0.1) ; extra == 'devel_azure'
Requires-Dist: azure-datalake-store (>=0.0.45) ; extra == 'devel_azure'
Requires-Dist: azure-mgmt-datalake-store (>=0.5.0) ; extra == 'devel_azure'
Requires-Dist: azure-mgmt-resource (>=2.2.0) ; extra == 'devel_azure'
Requires-Dist: azure-identity (>=1.3.1) ; extra == 'devel_azure'
Requires-Dist: azure-keyvault (>=4.1.0) ; extra == 'devel_azure'
Requires-Dist: boto3 (~=1.10) ; extra == 'devel_azure'
Requires-Dist: cgroupspy (>=0.1.4) ; extra == 'devel_azure'
Requires-Dist: beautifulsoup4 (~=4.7.1) ; extra == 'devel_azure'
Requires-Dist: click (==6.7) ; extra == 'devel_azure'
Requires-Dist: coverage ; extra == 'devel_azure'
Requires-Dist: docutils (<0.16,>=0.14) ; extra == 'devel_azure'
Requires-Dist: ecdsa (<0.15) ; extra == 'devel_azure'
Requires-Dist: flake8 (>=3.6.0) ; extra == 'devel_azure'
Requires-Dist: flake8-colors ; extra == 'devel_azure'
Requires-Dist: flaky ; extra == 'devel_azure'
Requires-Dist: freezegun ; extra == 'devel_azure'
Requires-Dist: gitpython ; extra == 'devel_azure'
Requires-Dist: idna (<2.9) ; extra == 'devel_azure'
Requires-Dist: ipdb ; extra == 'devel_azure'
Requires-Dist: jira ; extra == 'devel_azure'
Requires-Dist: mongomock ; extra == 'devel_azure'
Requires-Dist: moto (==1.3.14) ; extra == 'devel_azure'
Requires-Dist: packaging ; extra == 'devel_azure'
Requires-Dist: parameterized ; extra == 'devel_azure'
Requires-Dist: paramiko ; extra == 'devel_azure'
Requires-Dist: pipdeptree ; extra == 'devel_azure'
Requires-Dist: pre-commit ; extra == 'devel_azure'
Requires-Dist: pysftp ; extra == 'devel_azure'
Requires-Dist: pytest (<6.0.0) ; extra == 'devel_azure'
Requires-Dist: pytest-cov ; extra == 'devel_azure'
Requires-Dist: pytest-instafail ; extra == 'devel_azure'
Requires-Dist: pytest-timeouts ; extra == 'devel_azure'
Requires-Dist: pywinrm ; extra == 'devel_azure'
Requires-Dist: qds-sdk (>=1.9.6) ; extra == 'devel_azure'
Requires-Dist: requests-mock ; extra == 'devel_azure'
Requires-Dist: yamllint ; extra == 'devel_azure'
Requires-Dist: mypy (==0.720) ; extra == 'devel_azure'
Requires-Dist: sphinx-argparse (>=0.1.13) ; extra == 'devel_azure'
Requires-Dist: sphinx-autoapi (==1.0.0) ; extra == 'devel_azure'
Requires-Dist: sphinx-jinja (~=1.1) ; extra == 'devel_azure'
Requires-Dist: sphinx-rtd-theme (>=0.1.6) ; extra == 'devel_azure'
Requires-Dist: sphinxcontrib-httpdomain (>=1.7.0) ; extra == 'devel_azure'
Requires-Dist: cryptography (>=2.0.0) ; extra == 'devel_azure'
Requires-Dist: kubernetes (<12.0.0,>=3.0.0) ; extra == 'devel_azure'
Requires-Dist: mysqlclient (<1.4,>=1.3.6) ; extra == 'devel_azure'
Requires-Dist: bcrypt (>=2.0.0) ; extra == 'devel_azure'
Requires-Dist: flask-bcrypt (>=0.7.1) ; extra == 'devel_azure'
Requires-Dist: cffi (<1.14.0) ; (python_version < "3.0") and extra == 'devel_azure'
Requires-Dist: pyrsistent (<=0.16.0) ; (python_version < "3.0") and extra == 'devel_azure'
Requires-Dist: sphinx (==1.8.5) ; (python_version < "3.0") and extra == 'devel_azure'
Requires-Dist: mock ; (python_version < "3.3") and extra == 'devel_azure'
Requires-Dist: contextdecorator ; (python_version < "3.4") and extra == 'devel_azure'
Requires-Dist: azure-storage-blob (<12.0.0) ; (python_version < "3.6") and extra == 'devel_azure'
Requires-Dist: importlib-metadata (~=2.0) ; (python_version < "3.9") and extra == 'devel_azure'
Requires-Dist: pyrsistent ; (python_version >= "3.0") and extra == 'devel_azure'
Requires-Dist: sphinx (>=2.1.2) ; (python_version >= "3.0") and extra == 'devel_azure'
Requires-Dist: azure-storage-blob ; (python_version >= "3.6") and extra == 'devel_azure'
Requires-Dist: sphinx-copybutton ; (python_version >= "3.6") and extra == 'devel_azure'
Provides-Extra: devel_ci
Requires-Dist: cassandra-driver (<3.21.0,>=3.13.0) ; extra == 'devel_ci'
Requires-Dist: cloudant (<2.0,>=0.5.9) ; extra == 'devel_ci'
Requires-Dist: pydruid (<=0.5.8,>=0.4.1) ; extra == 'devel_ci'
Requires-Dist: hmsclient (>=0.1.0) ; extra == 'devel_ci'
Requires-Dist: pyhive[hive] (>=0.6.0) ; extra == 'devel_ci'
Requires-Dist: dnspython (<2.0.0,>=1.13.0) ; extra == 'devel_ci'
Requires-Dist: pymongo (<3.11.0,>=3.6.0) ; extra == 'devel_ci'
Requires-Dist: mysqlclient (<1.4,>=1.3.6) ; extra == 'devel_ci'
Requires-Dist: pinotdb (==0.1.1) ; extra == 'devel_ci'
Requires-Dist: psycopg2-binary (>=2.7.4) ; extra == 'devel_ci'
Requires-Dist: presto-python-client (<0.8,>=0.7.0) ; extra == 'devel_ci'
Requires-Dist: vertica-python (>=0.5.1) ; extra == 'devel_ci'
Requires-Dist: atlasclient (>=0.1.2) ; extra == 'devel_ci'
Requires-Dist: boto3 (~=1.10) ; extra == 'devel_ci'
Requires-Dist: azure-storage (<0.37.0,>=0.34.0) ; extra == 'devel_ci'
Requires-Dist: azure-storage-common ; extra == 'devel_ci'
Requires-Dist: azure-mgmt-containerinstance (<2,>=1.5.0) ; extra == 'devel_ci'
Requires-Dist: azure-cosmos (<4,>=3.0.1) ; extra == 'devel_ci'
Requires-Dist: azure-datalake-store (>=0.0.45) ; extra == 'devel_ci'
Requires-Dist: azure-mgmt-datalake-store (>=0.5.0) ; extra == 'devel_ci'
Requires-Dist: azure-mgmt-resource (>=2.2.0) ; extra == 'devel_ci'
Requires-Dist: azure-identity (>=1.3.1) ; extra == 'devel_ci'
Requires-Dist: azure-keyvault (>=4.1.0) ; extra == 'devel_ci'
Requires-Dist: cgroupspy (>=0.1.4) ; extra == 'devel_ci'
Requires-Dist: beautifulsoup4 (~=4.7.1) ; extra == 'devel_ci'
Requires-Dist: click (==6.7) ; extra == 'devel_ci'
Requires-Dist: coverage ; extra == 'devel_ci'
Requires-Dist: docutils (<0.16,>=0.14) ; extra == 'devel_ci'
Requires-Dist: ecdsa (<0.15) ; extra == 'devel_ci'
Requires-Dist: flake8 (>=3.6.0) ; extra == 'devel_ci'
Requires-Dist: flake8-colors ; extra == 'devel_ci'
Requires-Dist: flaky ; extra == 'devel_ci'
Requires-Dist: freezegun ; extra == 'devel_ci'
Requires-Dist: gitpython ; extra == 'devel_ci'
Requires-Dist: idna (<2.9) ; extra == 'devel_ci'
Requires-Dist: ipdb ; extra == 'devel_ci'
Requires-Dist: jira ; extra == 'devel_ci'
Requires-Dist: mongomock ; extra == 'devel_ci'
Requires-Dist: moto (==1.3.14) ; extra == 'devel_ci'
Requires-Dist: packaging ; extra == 'devel_ci'
Requires-Dist: parameterized ; extra == 'devel_ci'
Requires-Dist: paramiko ; extra == 'devel_ci'
Requires-Dist: pipdeptree ; extra == 'devel_ci'
Requires-Dist: pre-commit ; extra == 'devel_ci'
Requires-Dist: pysftp ; extra == 'devel_ci'
Requires-Dist: pytest (<6.0.0) ; extra == 'devel_ci'
Requires-Dist: pytest-cov ; extra == 'devel_ci'
Requires-Dist: pytest-instafail ; extra == 'devel_ci'
Requires-Dist: pytest-timeouts ; extra == 'devel_ci'
Requires-Dist: pywinrm ; extra == 'devel_ci'
Requires-Dist: qds-sdk (>=1.9.6) ; extra == 'devel_ci'
Requires-Dist: requests-mock ; extra == 'devel_ci'
Requires-Dist: yamllint ; extra == 'devel_ci'
Requires-Dist: mypy (==0.720) ; extra == 'devel_ci'
Requires-Dist: sphinx-argparse (>=0.1.13) ; extra == 'devel_ci'
Requires-Dist: sphinx-autoapi (==1.0.0) ; extra == 'devel_ci'
Requires-Dist: sphinx-jinja (~=1.1) ; extra == 'devel_ci'
Requires-Dist: sphinx-rtd-theme (>=0.1.6) ; extra == 'devel_ci'
Requires-Dist: sphinxcontrib-httpdomain (>=1.7.0) ; extra == 'devel_ci'
Requires-Dist: cryptography (>=2.0.0) ; extra == 'devel_ci'
Requires-Dist: kubernetes (<12.0.0,>=3.0.0) ; extra == 'devel_ci'
Requires-Dist: bcrypt (>=2.0.0) ; extra == 'devel_ci'
Requires-Dist: flask-bcrypt (>=0.7.1) ; extra == 'devel_ci'
Requires-Dist: flower (<1.0,>=0.7.3) ; extra == 'devel_ci'
Requires-Dist: tornado (<6.0,>=4.2.0) ; extra == 'devel_ci'
Requires-Dist: vine (~=1.3) ; extra == 'devel_ci'
Requires-Dist: datadog (>=0.14.0) ; extra == 'devel_ci'
Requires-Dist: docker (~=3.0) ; extra == 'devel_ci'
Requires-Dist: elasticsearch (<6.0.0,>=5.0.0) ; extra == 'devel_ci'
Requires-Dist: elasticsearch-dsl (<6.0.0,>=5.0.0) ; extra == 'devel_ci'
Requires-Dist: google-api-python-client (<2.0.0,>=1.6.0) ; extra == 'devel_ci'
Requires-Dist: google-auth (<2.0.0,>=1.0.0) ; extra == 'devel_ci'
Requires-Dist: google-auth-httplib2 (>=0.0.1) ; extra == 'devel_ci'
Requires-Dist: google-cloud-bigtable (<2.0.0,>=1.0.0) ; extra == 'devel_ci'
Requires-Dist: google-cloud-container (<2.0.0,>=0.1.1) ; extra == 'devel_ci'
Requires-Dist: google-cloud-dlp (<2.0.0,>=0.11.0) ; extra == 'devel_ci'
Requires-Dist: google-cloud-language (<2.0.0,>=1.1.1) ; extra == 'devel_ci'
Requires-Dist: google-cloud-secret-manager (<2.0.0,>=0.2.0) ; extra == 'devel_ci'
Requires-Dist: google-cloud-spanner (<2.0.0,>=1.10.0) ; extra == 'devel_ci'
Requires-Dist: google-cloud-speech (<2.0.0,>=0.36.3) ; extra == 'devel_ci'
Requires-Dist: google-cloud-storage (<2.0.0,>=1.16) ; extra == 'devel_ci'
Requires-Dist: google-cloud-texttospeech (<2,>=0.4.0) ; extra == 'devel_ci'
Requires-Dist: google-cloud-translate (<2.0.0,>=1.3.3) ; extra == 'devel_ci'
Requires-Dist: google-cloud-videointelligence (<2.0.0,>=1.7.0) ; extra == 'devel_ci'
Requires-Dist: google-cloud-vision (<2.0.0,>=0.35.2) ; extra == 'devel_ci'
Requires-Dist: grpcio-gcp (>=0.2.2) ; extra == 'devel_ci'
Requires-Dist: pandas-gbq ; extra == 'devel_ci'
Requires-Dist: grpcio (>=1.15.0) ; extra == 'devel_ci'
Requires-Dist: hvac (~=0.10) ; extra == 'devel_ci'
Requires-Dist: JPype1 (==0.7.1) ; extra == 'devel_ci'
Requires-Dist: jaydebeapi (>=1.1.1) ; extra == 'devel_ci'
Requires-Dist: python-jenkins (>=1.0.0) ; extra == 'devel_ci'
Requires-Dist: pykerberos (>=1.1.13) ; extra == 'devel_ci'
Requires-Dist: requests-kerberos (>=0.10.0) ; extra == 'devel_ci'
Requires-Dist: ldap3 (>=2.5.1) ; extra == 'devel_ci'
Requires-Dist: papermill[all] (>=1.0.0) ; extra == 'devel_ci'
Requires-Dist: nteract-scrapbook[all] (>=0.2.1) ; extra == 'devel_ci'
Requires-Dist: pyarrow (<1.0.0) ; extra == 'devel_ci'
Requires-Dist: amqp (<5.0.0) ; extra == 'devel_ci'
Requires-Dist: redis (~=3.2) ; extra == 'devel_ci'
Requires-Dist: pysmbclient (>=0.1.3) ; extra == 'devel_ci'
Requires-Dist: analytics-python (>=1.2.9) ; extra == 'devel_ci'
Requires-Dist: sendgrid (<6,>=5.2.0) ; extra == 'devel_ci'
Requires-Dist: blinker (>=1.1) ; extra == 'devel_ci'
Requires-Dist: sentry-sdk (>=0.8.0) ; extra == 'devel_ci'
Requires-Dist: slackclient (<2.0.0,>=1.0.0) ; extra == 'devel_ci'
Requires-Dist: websocket-client (<0.55.0) ; extra == 'devel_ci'
Requires-Dist: boto3 (<1.11) ; extra == 'devel_ci'
Requires-Dist: snowflake-connector-python (>=1.5.2) ; extra == 'devel_ci'
Requires-Dist: snowflake-sqlalchemy (>=1.1.0) ; extra == 'devel_ci'
Requires-Dist: paramiko (>=2.1.1) ; extra == 'devel_ci'
Requires-Dist: pysftp (>=0.2.9) ; extra == 'devel_ci'
Requires-Dist: sshtunnel (<0.2,>=0.1.4) ; extra == 'devel_ci'
Requires-Dist: virtualenv ; extra == 'devel_ci'
Requires-Dist: hdfs[avro,dataframe,kerberos] (>=2.0.4) ; extra == 'devel_ci'
Requires-Dist: zdesk ; extra == 'devel_ci'
Requires-Dist: snakebite (>=2.7.8) ; (python_version < "3.0") and extra == 'devel_ci'
Requires-Dist: cffi (<1.14.0) ; (python_version < "3.0") and extra == 'devel_ci'
Requires-Dist: pyrsistent (<=0.16.0) ; (python_version < "3.0") and extra == 'devel_ci'
Requires-Dist: sphinx (==1.8.5) ; (python_version < "3.0") and extra == 'devel_ci'
Requires-Dist: celery (==4.3.1) ; (python_version < "3.0") and extra == 'devel_ci'
Requires-Dist: kombu (==4.6.3) ; (python_version < "3.0") and extra == 'devel_ci'
Requires-Dist: cryptography (<3.0,>=0.9.3) ; (python_version < "3.0") and extra == 'devel_ci'
Requires-Dist: PyOpenSSL (<20.0.0) ; (python_version < "3.0") and extra == 'devel_ci'
Requires-Dist: thrift-sasl (<0.4.1,>=0.2.0) ; (python_version < "3.0") and extra == 'devel_ci'
Requires-Dist: cx-Oracle (<8.0,>=5.1.2) ; (python_version < "3.0") and extra == 'devel_ci'
Requires-Dist: mock ; (python_version < "3.3") and extra == 'devel_ci'
Requires-Dist: contextdecorator ; (python_version < "3.4") and extra == 'devel_ci'
Requires-Dist: azure-storage-blob (<12.0.0) ; (python_version < "3.6") and extra == 'devel_ci'
Requires-Dist: importlib-metadata (~=2.0) ; (python_version < "3.9") and extra == 'devel_ci'
Requires-Dist: fsspec (<0.8.0) ; (python_version == "3.5") and extra == 'devel_ci'
Requires-Dist: snakebite-py3 ; (python_version >= "3.0") and extra == 'devel_ci'
Requires-Dist: pyrsistent ; (python_version >= "3.0") and extra == 'devel_ci'
Requires-Dist: sphinx (>=2.1.2) ; (python_version >= "3.0") and extra == 'devel_ci'
Requires-Dist: celery (~=4.3) ; (python_version >= "3.0") and extra == 'devel_ci'
Requires-Dist: cryptography (>=0.9.3) ; (python_version >= "3.0") and extra == 'devel_ci'
Requires-Dist: PyOpenSSL ; (python_version >= "3.0") and extra == 'devel_ci'
Requires-Dist: thrift-sasl (>=0.2.0) ; (python_version >= "3.0") and extra == 'devel_ci'
Requires-Dist: cx-Oracle (>=5.1.2) ; (python_version >= "3.0") and extra == 'devel_ci'
Requires-Dist: azure-storage-blob ; (python_version >= "3.6") and extra == 'devel_ci'
Requires-Dist: sphinx-copybutton ; (python_version >= "3.6") and extra == 'devel_ci'
Requires-Dist: black (==20.8b0) ; (python_version >= "3.6") and extra == 'devel_ci'
Provides-Extra: devel_hadoop
Requires-Dist: boto3 (~=1.10) ; extra == 'devel_hadoop'
Requires-Dist: cgroupspy (>=0.1.4) ; extra == 'devel_hadoop'
Requires-Dist: beautifulsoup4 (~=4.7.1) ; extra == 'devel_hadoop'
Requires-Dist: click (==6.7) ; extra == 'devel_hadoop'
Requires-Dist: coverage ; extra == 'devel_hadoop'
Requires-Dist: docutils (<0.16,>=0.14) ; extra == 'devel_hadoop'
Requires-Dist: ecdsa (<0.15) ; extra == 'devel_hadoop'
Requires-Dist: flake8 (>=3.6.0) ; extra == 'devel_hadoop'
Requires-Dist: flake8-colors ; extra == 'devel_hadoop'
Requires-Dist: flaky ; extra == 'devel_hadoop'
Requires-Dist: freezegun ; extra == 'devel_hadoop'
Requires-Dist: gitpython ; extra == 'devel_hadoop'
Requires-Dist: idna (<2.9) ; extra == 'devel_hadoop'
Requires-Dist: ipdb ; extra == 'devel_hadoop'
Requires-Dist: jira ; extra == 'devel_hadoop'
Requires-Dist: mongomock ; extra == 'devel_hadoop'
Requires-Dist: moto (==1.3.14) ; extra == 'devel_hadoop'
Requires-Dist: packaging ; extra == 'devel_hadoop'
Requires-Dist: parameterized ; extra == 'devel_hadoop'
Requires-Dist: paramiko ; extra == 'devel_hadoop'
Requires-Dist: pipdeptree ; extra == 'devel_hadoop'
Requires-Dist: pre-commit ; extra == 'devel_hadoop'
Requires-Dist: pysftp ; extra == 'devel_hadoop'
Requires-Dist: pytest (<6.0.0) ; extra == 'devel_hadoop'
Requires-Dist: pytest-cov ; extra == 'devel_hadoop'
Requires-Dist: pytest-instafail ; extra == 'devel_hadoop'
Requires-Dist: pytest-timeouts ; extra == 'devel_hadoop'
Requires-Dist: pywinrm ; extra == 'devel_hadoop'
Requires-Dist: qds-sdk (>=1.9.6) ; extra == 'devel_hadoop'
Requires-Dist: requests-mock ; extra == 'devel_hadoop'
Requires-Dist: yamllint ; extra == 'devel_hadoop'
Requires-Dist: mypy (==0.720) ; extra == 'devel_hadoop'
Requires-Dist: sphinx-argparse (>=0.1.13) ; extra == 'devel_hadoop'
Requires-Dist: sphinx-autoapi (==1.0.0) ; extra == 'devel_hadoop'
Requires-Dist: sphinx-jinja (~=1.1) ; extra == 'devel_hadoop'
Requires-Dist: sphinx-rtd-theme (>=0.1.6) ; extra == 'devel_hadoop'
Requires-Dist: sphinxcontrib-httpdomain (>=1.7.0) ; extra == 'devel_hadoop'
Requires-Dist: cryptography (>=2.0.0) ; extra == 'devel_hadoop'
Requires-Dist: kubernetes (<12.0.0,>=3.0.0) ; extra == 'devel_hadoop'
Requires-Dist: mysqlclient (<1.4,>=1.3.6) ; extra == 'devel_hadoop'
Requires-Dist: bcrypt (>=2.0.0) ; extra == 'devel_hadoop'
Requires-Dist: flask-bcrypt (>=0.7.1) ; extra == 'devel_hadoop'
Requires-Dist: hmsclient (>=0.1.0) ; extra == 'devel_hadoop'
Requires-Dist: pyhive[hive] (>=0.6.0) ; extra == 'devel_hadoop'
Requires-Dist: pykerberos (>=1.1.13) ; extra == 'devel_hadoop'
Requires-Dist: requests-kerberos (>=0.10.0) ; extra == 'devel_hadoop'
Requires-Dist: presto-python-client (<0.8,>=0.7.0) ; extra == 'devel_hadoop'
Requires-Dist: hdfs[avro,dataframe,kerberos] (>=2.0.4) ; extra == 'devel_hadoop'
Requires-Dist: pyrsistent (<=0.16.0) ; (python_version < "3.0") and extra == 'devel_hadoop'
Requires-Dist: sphinx (==1.8.5) ; (python_version < "3.0") and extra == 'devel_hadoop'
Requires-Dist: snakebite (>=2.7.8) ; (python_version < "3.0") and extra == 'devel_hadoop'
Requires-Dist: thrift-sasl (<0.4.1,>=0.2.0) ; (python_version < "3.0") and extra == 'devel_hadoop'
Requires-Dist: mock ; (python_version < "3.3") and extra == 'devel_hadoop'
Requires-Dist: contextdecorator ; (python_version < "3.4") and extra == 'devel_hadoop'
Requires-Dist: importlib-metadata (~=2.0) ; (python_version < "3.9") and extra == 'devel_hadoop'
Requires-Dist: pyrsistent ; (python_version >= "3.0") and extra == 'devel_hadoop'
Requires-Dist: sphinx (>=2.1.2) ; (python_version >= "3.0") and extra == 'devel_hadoop'
Requires-Dist: snakebite-py3 ; (python_version >= "3.0") and extra == 'devel_hadoop'
Requires-Dist: thrift-sasl (>=0.2.0) ; (python_version >= "3.0") and extra == 'devel_hadoop'
Requires-Dist: sphinx-copybutton ; (python_version >= "3.6") and extra == 'devel_hadoop'
Provides-Extra: doc
Requires-Dist: sphinx-argparse (>=0.1.13) ; extra == 'doc'
Requires-Dist: sphinx-autoapi (==1.0.0) ; extra == 'doc'
Requires-Dist: sphinx-jinja (~=1.1) ; extra == 'doc'
Requires-Dist: sphinx-rtd-theme (>=0.1.6) ; extra == 'doc'
Requires-Dist: sphinxcontrib-httpdomain (>=1.7.0) ; extra == 'doc'
Requires-Dist: sphinx (==1.8.5) ; (python_version < "3.0") and extra == 'doc'
Requires-Dist: sphinx (>=2.1.2) ; (python_version >= "3.0") and extra == 'doc'
Requires-Dist: sphinx-copybutton ; (python_version >= "3.6") and extra == 'doc'
Provides-Extra: docker
Requires-Dist: docker (~=3.0) ; extra == 'docker'
Provides-Extra: druid
Requires-Dist: pydruid (<=0.5.8,>=0.4.1) ; extra == 'druid'
Provides-Extra: elasticsearch
Requires-Dist: elasticsearch (<6.0.0,>=5.0.0) ; extra == 'elasticsearch'
Requires-Dist: elasticsearch-dsl (<6.0.0,>=5.0.0) ; extra == 'elasticsearch'
Provides-Extra: emr
Requires-Dist: boto3 (~=1.10) ; extra == 'emr'
Provides-Extra: gcp
Requires-Dist: google-api-python-client (<2.0.0,>=1.6.0) ; extra == 'gcp'
Requires-Dist: google-auth (<2.0.0,>=1.0.0) ; extra == 'gcp'
Requires-Dist: google-auth-httplib2 (>=0.0.1) ; extra == 'gcp'
Requires-Dist: google-cloud-bigtable (<2.0.0,>=1.0.0) ; extra == 'gcp'
Requires-Dist: google-cloud-container (<2.0.0,>=0.1.1) ; extra == 'gcp'
Requires-Dist: google-cloud-dlp (<2.0.0,>=0.11.0) ; extra == 'gcp'
Requires-Dist: google-cloud-language (<2.0.0,>=1.1.1) ; extra == 'gcp'
Requires-Dist: google-cloud-secret-manager (<2.0.0,>=0.2.0) ; extra == 'gcp'
Requires-Dist: google-cloud-spanner (<2.0.0,>=1.10.0) ; extra == 'gcp'
Requires-Dist: google-cloud-speech (<2.0.0,>=0.36.3) ; extra == 'gcp'
Requires-Dist: google-cloud-storage (<2.0.0,>=1.16) ; extra == 'gcp'
Requires-Dist: google-cloud-texttospeech (<2,>=0.4.0) ; extra == 'gcp'
Requires-Dist: google-cloud-translate (<2.0.0,>=1.3.3) ; extra == 'gcp'
Requires-Dist: google-cloud-videointelligence (<2.0.0,>=1.7.0) ; extra == 'gcp'
Requires-Dist: google-cloud-vision (<2.0.0,>=0.35.2) ; extra == 'gcp'
Requires-Dist: grpcio-gcp (>=0.2.2) ; extra == 'gcp'
Requires-Dist: pandas-gbq ; extra == 'gcp'
Requires-Dist: PyOpenSSL (<20.0.0) ; (python_version < "3.0") and extra == 'gcp'
Requires-Dist: PyOpenSSL ; (python_version >= "3.0") and extra == 'gcp'
Provides-Extra: gcp_api
Requires-Dist: google-api-python-client (<2.0.0,>=1.6.0) ; extra == 'gcp_api'
Requires-Dist: google-auth (<2.0.0,>=1.0.0) ; extra == 'gcp_api'
Requires-Dist: google-auth-httplib2 (>=0.0.1) ; extra == 'gcp_api'
Requires-Dist: google-cloud-bigtable (<2.0.0,>=1.0.0) ; extra == 'gcp_api'
Requires-Dist: google-cloud-container (<2.0.0,>=0.1.1) ; extra == 'gcp_api'
Requires-Dist: google-cloud-dlp (<2.0.0,>=0.11.0) ; extra == 'gcp_api'
Requires-Dist: google-cloud-language (<2.0.0,>=1.1.1) ; extra == 'gcp_api'
Requires-Dist: google-cloud-secret-manager (<2.0.0,>=0.2.0) ; extra == 'gcp_api'
Requires-Dist: google-cloud-spanner (<2.0.0,>=1.10.0) ; extra == 'gcp_api'
Requires-Dist: google-cloud-speech (<2.0.0,>=0.36.3) ; extra == 'gcp_api'
Requires-Dist: google-cloud-storage (<2.0.0,>=1.16) ; extra == 'gcp_api'
Requires-Dist: google-cloud-texttospeech (<2,>=0.4.0) ; extra == 'gcp_api'
Requires-Dist: google-cloud-translate (<2.0.0,>=1.3.3) ; extra == 'gcp_api'
Requires-Dist: google-cloud-videointelligence (<2.0.0,>=1.7.0) ; extra == 'gcp_api'
Requires-Dist: google-cloud-vision (<2.0.0,>=0.35.2) ; extra == 'gcp_api'
Requires-Dist: grpcio-gcp (>=0.2.2) ; extra == 'gcp_api'
Requires-Dist: pandas-gbq ; extra == 'gcp_api'
Requires-Dist: PyOpenSSL (<20.0.0) ; (python_version < "3.0") and extra == 'gcp_api'
Requires-Dist: PyOpenSSL ; (python_version >= "3.0") and extra == 'gcp_api'
Provides-Extra: github_enterprise
Requires-Dist: Flask-OAuthlib (<0.9.6,>=0.9.1) ; extra == 'github_enterprise'
Requires-Dist: oauthlib (!=2.0.3,!=2.0.4,!=2.0.5,<3.0.0,>=1.1.2) ; extra == 'github_enterprise'
Requires-Dist: requests-oauthlib (==1.1.0) ; extra == 'github_enterprise'
Provides-Extra: google
Requires-Dist: google-api-python-client (<2.0.0,>=1.6.0) ; extra == 'google'
Requires-Dist: google-auth (<2.0.0,>=1.0.0) ; extra == 'google'
Requires-Dist: google-auth-httplib2 (>=0.0.1) ; extra == 'google'
Requires-Dist: google-cloud-bigtable (<2.0.0,>=1.0.0) ; extra == 'google'
Requires-Dist: google-cloud-container (<2.0.0,>=0.1.1) ; extra == 'google'
Requires-Dist: google-cloud-dlp (<2.0.0,>=0.11.0) ; extra == 'google'
Requires-Dist: google-cloud-language (<2.0.0,>=1.1.1) ; extra == 'google'
Requires-Dist: google-cloud-secret-manager (<2.0.0,>=0.2.0) ; extra == 'google'
Requires-Dist: google-cloud-spanner (<2.0.0,>=1.10.0) ; extra == 'google'
Requires-Dist: google-cloud-speech (<2.0.0,>=0.36.3) ; extra == 'google'
Requires-Dist: google-cloud-storage (<2.0.0,>=1.16) ; extra == 'google'
Requires-Dist: google-cloud-texttospeech (<2,>=0.4.0) ; extra == 'google'
Requires-Dist: google-cloud-translate (<2.0.0,>=1.3.3) ; extra == 'google'
Requires-Dist: google-cloud-videointelligence (<2.0.0,>=1.7.0) ; extra == 'google'
Requires-Dist: google-cloud-vision (<2.0.0,>=0.35.2) ; extra == 'google'
Requires-Dist: grpcio-gcp (>=0.2.2) ; extra == 'google'
Requires-Dist: pandas-gbq ; extra == 'google'
Requires-Dist: PyOpenSSL (<20.0.0) ; (python_version < "3.0") and extra == 'google'
Requires-Dist: PyOpenSSL ; (python_version >= "3.0") and extra == 'google'
Provides-Extra: google_auth
Requires-Dist: Flask-OAuthlib (<0.9.6,>=0.9.1) ; extra == 'google_auth'
Requires-Dist: oauthlib (!=2.0.3,!=2.0.4,!=2.0.5,<3.0.0,>=1.1.2) ; extra == 'google_auth'
Requires-Dist: requests-oauthlib (==1.1.0) ; extra == 'google_auth'
Provides-Extra: grpc
Requires-Dist: grpcio (>=1.15.0) ; extra == 'grpc'
Provides-Extra: hashicorp
Requires-Dist: hvac (~=0.10) ; extra == 'hashicorp'
Provides-Extra: hdfs
Requires-Dist: snakebite (>=2.7.8) ; (python_version < "3.0") and extra == 'hdfs'
Requires-Dist: snakebite-py3 ; (python_version >= "3.0") and extra == 'hdfs'
Provides-Extra: hive
Requires-Dist: hmsclient (>=0.1.0) ; extra == 'hive'
Requires-Dist: pyhive[hive] (>=0.6.0) ; extra == 'hive'
Provides-Extra: jdbc
Requires-Dist: JPype1 (==0.7.1) ; extra == 'jdbc'
Requires-Dist: jaydebeapi (>=1.1.1) ; extra == 'jdbc'
Provides-Extra: jira
Requires-Dist: JIRA (>1.0.7) ; extra == 'jira'
Provides-Extra: kerberos
Requires-Dist: pykerberos (>=1.1.13) ; extra == 'kerberos'
Requires-Dist: requests-kerberos (>=0.10.0) ; extra == 'kerberos'
Requires-Dist: thrift-sasl (<0.4.1,>=0.2.0) ; (python_version < "3.0") and extra == 'kerberos'
Requires-Dist: thrift-sasl (>=0.2.0) ; (python_version >= "3.0") and extra == 'kerberos'
Provides-Extra: kubernetes
Requires-Dist: cryptography (>=2.0.0) ; extra == 'kubernetes'
Requires-Dist: kubernetes (<12.0.0,>=3.0.0) ; extra == 'kubernetes'
Provides-Extra: ldap
Requires-Dist: ldap3 (>=2.5.1) ; extra == 'ldap'
Provides-Extra: microsoft.azure
Requires-Dist: azure-storage (<0.37.0,>=0.34.0) ; extra == 'microsoft.azure'
Requires-Dist: azure-storage-common ; extra == 'microsoft.azure'
Requires-Dist: azure-mgmt-containerinstance (<2,>=1.5.0) ; extra == 'microsoft.azure'
Requires-Dist: azure-cosmos (<4,>=3.0.1) ; extra == 'microsoft.azure'
Requires-Dist: azure-datalake-store (>=0.0.45) ; extra == 'microsoft.azure'
Requires-Dist: azure-mgmt-datalake-store (>=0.5.0) ; extra == 'microsoft.azure'
Requires-Dist: azure-mgmt-resource (>=2.2.0) ; extra == 'microsoft.azure'
Requires-Dist: azure-identity (>=1.3.1) ; extra == 'microsoft.azure'
Requires-Dist: azure-keyvault (>=4.1.0) ; extra == 'microsoft.azure'
Requires-Dist: cffi (<1.14.0) ; (python_version < "3.0") and extra == 'microsoft.azure'
Requires-Dist: azure-storage-blob (<12.0.0) ; (python_version < "3.6") and extra == 'microsoft.azure'
Requires-Dist: azure-storage-blob ; (python_version >= "3.6") and extra == 'microsoft.azure'
Provides-Extra: microsoft.mssql
Requires-Dist: pymssql (~=2.1.1) ; extra == 'microsoft.mssql'
Provides-Extra: microsoft.winrm
Requires-Dist: pywinrm (~=0.4) ; extra == 'microsoft.winrm'
Provides-Extra: mongo
Requires-Dist: dnspython (<2.0.0,>=1.13.0) ; extra == 'mongo'
Requires-Dist: pymongo (<3.11.0,>=3.6.0) ; extra == 'mongo'
Provides-Extra: mssql
Requires-Dist: pymssql (~=2.1.1) ; extra == 'mssql'
Provides-Extra: mysql
Requires-Dist: mysqlclient (<1.4,>=1.3.6) ; extra == 'mysql'
Provides-Extra: oracle
Requires-Dist: cx-Oracle (<8.0,>=5.1.2) ; (python_version < "3.0") and extra == 'oracle'
Requires-Dist: cx-Oracle (>=5.1.2) ; (python_version >= "3.0") and extra == 'oracle'
Provides-Extra: papermill
Requires-Dist: papermill[all] (>=1.0.0) ; extra == 'papermill'
Requires-Dist: nteract-scrapbook[all] (>=0.2.1) ; extra == 'papermill'
Requires-Dist: pyarrow (<1.0.0) ; extra == 'papermill'
Requires-Dist: fsspec (<0.8.0) ; (python_version == "3.5") and extra == 'papermill'
Requires-Dist: black (==20.8b0) ; (python_version >= "3.6") and extra == 'papermill'
Provides-Extra: password
Requires-Dist: bcrypt (>=2.0.0) ; extra == 'password'
Requires-Dist: flask-bcrypt (>=0.7.1) ; extra == 'password'
Provides-Extra: pinot
Requires-Dist: pinotdb (==0.1.1) ; extra == 'pinot'
Provides-Extra: postgres
Requires-Dist: psycopg2-binary (>=2.7.4) ; extra == 'postgres'
Provides-Extra: presto
Requires-Dist: presto-python-client (<0.8,>=0.7.0) ; extra == 'presto'
Provides-Extra: qds
Requires-Dist: qds-sdk (>=1.10.4) ; extra == 'qds'
Provides-Extra: rabbitmq
Requires-Dist: amqp (<5.0.0) ; extra == 'rabbitmq'
Provides-Extra: redis
Requires-Dist: redis (~=3.2) ; extra == 'redis'
Provides-Extra: s3
Requires-Dist: boto3 (~=1.10) ; extra == 's3'
Provides-Extra: salesforce
Requires-Dist: simple-salesforce (<1.0.0,>=0.72) ; extra == 'salesforce'
Provides-Extra: samba
Requires-Dist: pysmbclient (>=0.1.3) ; extra == 'samba'
Provides-Extra: segment
Requires-Dist: analytics-python (>=1.2.9) ; extra == 'segment'
Provides-Extra: sendgrid
Requires-Dist: sendgrid (<6,>=5.2.0) ; extra == 'sendgrid'
Provides-Extra: sentry
Requires-Dist: blinker (>=1.1) ; extra == 'sentry'
Requires-Dist: sentry-sdk (>=0.8.0) ; extra == 'sentry'
Provides-Extra: slack
Requires-Dist: slackclient (<2.0.0,>=1.0.0) ; extra == 'slack'
Requires-Dist: websocket-client (<0.55.0) ; extra == 'slack'
Provides-Extra: snowflake
Requires-Dist: boto3 (<1.11) ; extra == 'snowflake'
Requires-Dist: snowflake-connector-python (>=1.5.2) ; extra == 'snowflake'
Requires-Dist: snowflake-sqlalchemy (>=1.1.0) ; extra == 'snowflake'
Provides-Extra: ssh
Requires-Dist: paramiko (>=2.1.1) ; extra == 'ssh'
Requires-Dist: pysftp (>=0.2.9) ; extra == 'ssh'
Requires-Dist: sshtunnel (<0.2,>=0.1.4) ; extra == 'ssh'
Provides-Extra: statsd
Requires-Dist: statsd (<4.0,>=3.3.0) ; extra == 'statsd'
Provides-Extra: vertica
Requires-Dist: vertica-python (>=0.5.1) ; extra == 'vertica'
Provides-Extra: virtualenv
Requires-Dist: virtualenv ; extra == 'virtualenv'
Provides-Extra: webhdfs
Requires-Dist: hdfs[avro,dataframe,kerberos] (>=2.0.4) ; extra == 'webhdfs'
Provides-Extra: winrm
Requires-Dist: pywinrm (~=0.4) ; extra == 'winrm'
